TechAdoption/Build_Model.py
TechAdoption/Predict_Model.py
TechAdoption/__init__.py
TechAdoption/execute.py
TechAdoption/Test/Test_Build_Model.py
TechAdoption/Test/__init__.py
TechAdoption-0.1.0.dist-info/LICENSE
TechAdoption-0.1.0.dist-info/METADATA
TechAdoption-0.1.0.dist-info/WHEEL
TechAdoption-0.1.0.dist-info/top_level.txt
TechAdoption-0.1.0.dist-info/RECORD
