Metadata-Version: 2.1
Name: TechAdoption
Version: 0.1.0
Summary: Identify top factors that predict rates of adoption
Home-page: https://github.com/Epeiffer1
Author: Erin Peiffer
Author-email: peiffer.erin@gmail.com
License: MIT-Clause
Platform: UNKNOWN
Classifier: License :: OSI Approved :: MIT License
Classifier: Natural Language :: English
Classifier: Programming Language :: Python :: 3
Requires-Python: >=3
